{
    "form_config": {
    "required_default": true
	},
        
  "nombre": {
    "type": "text",
    "label": "Nombre Provisional",
    "placeholder": "",
    "disabled": false,
    "validate": true,
    "animated_label": true,
    "value":"este es un ejemplo"
	},
        
    "password": {
    "type": "password",
    "label": "Password",
    "placeholder": "",
    "disabled": false,
    "validate": true,
    "animated_label": true,
    "value": ""
	},
        
    "color": {
    "type": "select",
    "label": "Color de Pelaje",
    "required": false,
    "options":{
        "0":{
             "tag":"Negro",
             "selected": true
            },
        "1":{
             "tag":"Macho",
             "disabled":true
            }
    }
	}
}